readme_generator/__init__.py
readme_generator/make_scaffold.py
readme_generator/scaffold_options.py
readme_generator/test_scaffold.py
write_me/__init__.py
write_me/conftest.py
write_me/dep_info.py
write_me/django_setings_info.py
write_me/django_uri_info.py
write_me/get_docstrings.py
write_me/get_license.py
write_me/git_description.py
write_me/list_files.py
write_me/list_imports.py
write_me/main_urls.py
write_me/project_data.py
write_me/project_urls.py
write_me/pyramid_ini.py
write_me/routes.py
write_me/stp_info.py
write_me/test_dep_info.py
write_me/test_django_setings_info.py
write_me/test_list_files.py
write_me/test_project_data.py
write_me/test_pyramid_ini.py
write_me/test_scaffold.py
write_me/test_stp_info.py
write_me/test_travis_badge.py
write_me/test_tsting_info.py
write_me/test_uri_info.py
write_me/travis_badge.py
write_me/tsting_info.py
write_me/urls.py
write_me-1.0.dist-info/DESCRIPTION.rst
write_me-1.0.dist-info/METADATA
write_me-1.0.dist-info/RECORD
write_me-1.0.dist-info/WHEEL
write_me-1.0.dist-info/entry_points.txt
write_me-1.0.dist-info/metadata.json
write_me-1.0.dist-info/top_level.txt
