Metadata-Version: 2.0
Name: write-me
Version: 1.0
Summary: Python package to assist developers with constructing README as project evolves.
Home-page: http://write-me.readthedocs.io/
Author: The write-me team: Chelsea Chris Matt Darren Gabe
Author-email: writeme.pypi@gmail.com
License: MIT
Download-URL: https://github.com/chelseadole/write-me/archive/1.0.tar.gz
Keywords: Python,README,PyPi,pip
Platform: UNKNOWN
Requires-Dist: markdown-generator
